tesseract_robotics_viewer/__init__.py
tesseract_robotics_viewer/tesseract_env_to_gltf.py
tesseract_robotics_viewer/tesseract_viewer.py
tesseract_robotics_viewer/tesseract_viewer_aio.py
tesseract_robotics_viewer/util.py
tesseract_robotics_viewer/resources/__init__.py
tesseract_robotics_viewer/resources/geometries.json
tesseract_robotics_viewer/resources/static/app.js
tesseract_robotics_viewer/resources/static/index.html
tesseract_robotics_viewer-0.5.0.dist-info/METADATA
tesseract_robotics_viewer-0.5.0.dist-info/WHEEL
tesseract_robotics_viewer-0.5.0.dist-info/top_level.txt
tesseract_robotics_viewer-0.5.0.dist-info/RECORD
